connect_umls/__init__.py
connect_umls/authentication.py
connect_umls/umls.py
connect_umls_pkg/__init__.py
connect_umls_pkg/authentication.py
connect_umls_pkg/umls.py
connect_umls-0.0.2.dist-info/LICENSE
connect_umls-0.0.2.dist-info/METADATA
connect_umls-0.0.2.dist-info/WHEEL
connect_umls-0.0.2.dist-info/top_level.txt
connect_umls-0.0.2.dist-info/RECORD
