Metadata-Version: 2.1
Name: connect-umls
Version: 0.0.2
Summary: Make connecting to the UMLS rest APIs easier
Home-page: https://gitlab.com/gracekatherineturner/umls_connect
Author: Grace Turner
Author-email: gracekatherineturner@gmail.com
License: UNKNOWN
Platform: UNKNOWN
Classifier: Programming Language :: Python :: 3
Classifier: License :: OSI Approved :: MIT License
Classifier: Operating System :: OS Independent
Requires-Python: >=3.6
